Workbook

Sheet JUNE 26
A1: INTEL HRC - ELECTRONIC CASH WALLET EXPENSE TRACKER
A2: DAILY CASH EXPENSE APPROVAL & TRACKING SHEET
A4: WALLET INFORMATION
A5: Opening Balance: | B5: 1795811 | D5: Date:11/06/2026 | H5: Wallet ID: | I5: MAVIANCE
A7: S/N | B7: DATE | C7: DESCRIPTION/PURPOSE | D7: BENEFICIARY | E7: CATEGORY | F7: AMOUNT REQUESTED (XAF) | G7: CFO APPROVAL | H7: CEO APPROVAL | I7: AMOUNT RELEASED (XAF) | J7: PAYMENT METHOD | K7: RECEIPT/REF NO. | L7: REMARKS
A8: 1 | B8: 46184 | C8: CLIENT REQUEST | D8: WARTSILA | E8: Miscellaneous | F8: 226500 | G8: APPROVED | H8: APPROVED | I8: =IF(AND(G8="APPROVED", OR(H8="", H8="APPROVED")), F8, "") -> 226500 | J8: Mobile Money | L8: 696000079
A9: 2 | B9: 46184 | C9: CARPENTER | D9: CLARISSE | E9: Utilities | F9: 15000 | G9: APPROVED | H9: APPROVED | I9: =IF(AND(G9="APPROVED", OR(H9="", H9="APPROVED")), F9, "") -> 15000 | J9: Mobile Money | L9: 673202213
A10: 3 | B10: 46184 | C10: INTERNET - STARLINK - HOME | D10: DNF | E10: Communication | F10: 56000 | G10: APPROVED | H10: APPROVED | I10: =IF(AND(G10="APPROVED", OR(H10="", H10="APPROVED")), F10, "") -> 56000 | J10: Mobile Money | L10: 691292582
A11: 4 | B11: 46184 | C11: HOME BOX STAFF | D11: Vera, Murielle, Désire, Modeste,Diane,and Enow | E11: Communication | F11: =25000*6 -> 150000 | G11: APPROVED | H11: APPROVED | I11: =IF(AND(G11="APPROVED", OR(H11="", H11="APPROVED")), F11, "") -> 150000 | J11: Mobile Money | L11: 680119289
A12: 5 | B12: 46184 | C12: OFFICE TRASHCAN | D12: VERA | E12: Utilities | F12: 50000 | G12: APPROVED | H12: APPROVED | I12: =IF(AND(G12="APPROVED", OR(H12="", H12="APPROVED")), F12, "") -> 50000 | J12: Mobile Money | L12: 656199170
A13: 6 | B13: 46184 | C13: SALARY | D13: 3C CAMEROUN | E13: Miscellaneous | F13: 64370 | G13: APPROVED | H13: APPROVED | I13: =IF(AND(G13="APPROVED", OR(H13="", H13="APPROVED")), F13, "") -> 64370 | J13: Mobile Money | L13: 690628016
A14: 7 | B14: 46184 | C14: OFFICE SUPPLIES - water,glasses,paper napkin, office toiletries | D14: CLARISSE | E14: Supplies | F14: 100000 | G14: APPROVED | H14: APPROVED | I14: =IF(AND(G14="APPROVED", OR(H14="", H14="APPROVED")), F14, "") -> 100000 | J14: Mobile Money | L14: 673202213
A15: 8 | B15: 46184 | C15: STAR LINK RENTALS | D15: IBSIRE CORPORATE | E15: Communication | F15: 45000 | G15: REJECTED | I15: =IF(AND(G15="APPROVED", OR(H15="", H15="APPROVED")), F15, "") | J15: Mobile Money
A16: 9 | B16: 46184 | C16: CHARGES | D16: CLARISSE | E16: Miscellaneous | F16: 1400 | G16: APPROVED | H16: APPROVED | I16: =IF(AND(G16="APPROVED", OR(H16="", H16="APPROVED")), F16, "") -> 1400 | J16: Mobile Money | L16: 673202213
A17: 10 | B17: 46184 | C17: CHARGES | D17: TINA | E17: Miscellaneous | F17: 1800 | G17: APPROVED | H17: APPROVED | I17: =IF(AND(G17="APPROVED", OR(H17="", H17="APPROVED")), F17, "") -> 1800 | J17: Mobile Money | L17: 680119289
A18: 11 | B18: 46188 | C18: EXTRA COST STARLINK - DNF | D18: FRANCIS | E18: Communication | F18: 5500 | G18: APPROVED | H18: APPROVED | I18: =IF(AND(G18="APPROVED", OR(H18="", H18="APPROVED")), F18, "") -> 5500 | J18: Mobile Money
A19: 12 | B19: 46188 | C19: FRAIS DE TAXI | D19: ERNEST | E19: Transport | F19: 3000 | G19: APPROVED | H19: APPROVED | I19: =IF(AND(G19="APPROVED", OR(H19="", H19="APPROVED")), F19, "") -> 3000 | J19: Mobile Money
A20: 13 | B20: 46188 | C20: DESIRE | D20: DESIRE | E20: Transport | F20: 10000 | G20: APPROVED | H20: APPROVED | I20: =IF(AND(G20="APPROVED", OR(H20="", H20="APPROVED")), F20, "") -> 10000 | J20: Mobile Money
A21: 14 | I21: =IF(AND(G21="APPROVED", OR(H21="", H21="APPROVED")), F21, "")
A22: 15 | I22: =IF(AND(G22="APPROVED", OR(H22="", H22="APPROVED")), F22, "")
A23: 16 | I23: =IF(AND(G23="APPROVED", OR(H23="", H23="APPROVED")), F23, "")
A24: 17 | I24: =IF(AND(G24="APPROVED", OR(H24="", H24="APPROVED")), F24, "")
A25: 18 | I25: =IF(AND(G25="APPROVED", OR(H25="", H25="APPROVED")), F25, "")
A26: 19 | I26: =IF(AND(G26="APPROVED", OR(H26="", H26="APPROVED")), F26, "")
A27: 20 | I27: =IF(AND(G27="APPROVED", OR(H27="", H27="APPROVED")), F27, "")
A28: TOTALS | F28: =SUM(F8:F27) -> 728570 | I28: =SUMIF(G8:G27,"APPROVED",I8:I27) -> 683570
A30: DAILY WALLET SUMMARY
A31: Opening Balance: | D31: 1795811
A32: Total Amount Requested: | D32: =F28 -> 728570
A33: Total Amount Released: | D33: =I28 -> 683570
A34: Pending Approval: | D34: =SUMIFS(F8:F27,G8:G27,"PENDING")+SUMIFS(F8:F27,G8:G27,"APPROVED",H8:H27,"PENDING") -> 0
A35: Rejected Amount: | D35: =SUMIF(G8:G27,"REJECTED",F8:F27)+SUMIFS(F8:F27,G8:G27,"APPROVED",H8:H27,"REJECTED") -> 45000
A36: Closing Balance: | D36: =D31-D33 -> 1112241
A39: AUTHORIZATION SIGNATURES
A41: Prepared By: Tina-Randa | D41: Reviewed By (Finance): | G41: CFO APPROVAL: | H41: ENOW | J41: CEO APPROVAL: | K41: DERICK FONDERSON
A42: Name/Date: 11/06/2026 | D42: Name/Date: | G42: Name/Date: | H42: 46184 | J42: Name/Date: | K42: 46184
A43: NOTE: CFO can approve expenses up to a defined threshold without CEO approval. Expenses above threshold require both CFO and CEO approval.

Sheet 11-06-2026
A1: INTEL HRC - ELECTRONIC CASH WALLET EXPENSE TRACKER
A2: DAILY CASH EXPENSE APPROVAL & TRACKING SHEET
A4: WALLET INFORMATION
A5: Opening Balance: | B5: 1795811 | D5: Date:11/06/2026 | H5: Wallet ID: | I5: MAVIANCE
A7: S/N | B7: DATE | C7: DESCRIPTION/PURPOSE | D7: BENEFICIARY | E7: CATEGORY | F7: AMOUNT REQUESTED (XAF) | G7: CFO APPROVAL | H7: CEO APPROVAL | I7: AMOUNT RELEASED (XAF) | J7: PAYMENT METHOD | K7: RECEIPT/REF NO. | L7: REMARKS
A8: 1 | B8: 46184 | C8: CLIENT REQUEST | D8: WARTSILA | E8: Client Expense | F8: 226500 | G8: APPROVED | H8: APPROVED | I8: =IF(OR(G8="REJECTED",G8=""),0,IF(OR(AND(G8="APPROVED",H8="APPROVED"),AND(G8="APPROVED",H8="")),F8,0)) -> 226500 | J8: Mobile Money | L8: 696000079
A9: 2 | B9: 46184 | C9: CARPENTER | D9: CLARISSE | E9: Utilities | F9: 15000 | G9: APPROVED | H9: APPROVED | I9: =IF(OR(G9="REJECTED",G9=""),0,IF(OR(AND(G9="APPROVED",H9="APPROVED"),AND(G9="APPROVED",H9="")),F9,0)) -> 15000 | J9: Mobile Money | L9: 673202213
A10: 4 | B10: 46184 | C10: HOME BOX STAFF | D10: Vera, Murielle, Désire, Modeste,Diane,and Enow | E10: Communication | F10: 150000 | G10: APPROVED | H10: APPROVED | I10: =IF(OR(G10="REJECTED",G10=""),0,IF(OR(AND(G10="APPROVED",H10="APPROVED"),AND(G10="APPROVED",H10="")),F10,0)) -> 150000 | J10: Mobile Money | L10: 680119289
A11: 5 | B11: 46184 | C11: OFFICE TRASHCAN | D11: VERA | E11: Utilities | F11: 51000 | G11: APPROVED | H11: APPROVED | I11: =IF(OR(G11="REJECTED",G11=""),0,IF(OR(AND(G11="APPROVED",H11="APPROVED"),AND(G11="APPROVED",H11="")),F11,0)) -> 51000 | J11: Mobile Money | L11: 656199170
A12: 7 | B12: 46184 | C12: OFFICE SUPPLIES - water,glasses,paper napkin, office toiletries | D12: CLARISSE | E12: Supplies | F12: 100000 | G12: APPROVED | H12: APPROVED | I12: =IF(OR(G12="REJECTED",G12=""),0,IF(OR(AND(G12="APPROVED",H12="APPROVED"),AND(G12="APPROVED",H12="")),F12,0)) -> 100000 | J12: Mobile Money | L12: 673202213
A13: 8 | B13: 46184 | C13: STAR LINK RENTALS | D13: IBSIRE CORPORATE | E13: Communication | F13: 45000 | G13: REJECTED | I13: =IF(OR(G13="REJECTED",G13=""),0,IF(OR(AND(G13="APPROVED",H13="APPROVED"),AND(G13="APPROVED",H13="")),F13,0)) -> 0 | J13: Mobile Money
A14: 9 | B14: 46184 | C14: CHARGES | D14: CLARISSE | E14: Miscellaneous | F14: 1400 | G14: APPROVED | H14: APPROVED | I14: =IF(OR(G14="REJECTED",G14=""),0,IF(OR(AND(G14="APPROVED",H14="APPROVED"),AND(G14="APPROVED",H14="")),F14,0)) -> 1400 | J14: Mobile Money | L14: 673202213
A15: 10 | B15: 46184 | C15: CHARGES | D15: TINA | E15: Miscellaneous | F15: 1800 | G15: APPROVED | H15: APPROVED | I15: =IF(OR(G15="REJECTED",G15=""),0,IF(OR(AND(G15="APPROVED",H15="APPROVED"),AND(G15="APPROVED",H15="")),F15,0)) -> 1800 | J15: Mobile Money | L15: 680119289
A16: 11 | I16: =IF(OR(G16="REJECTED",G16=""),0,IF(OR(AND(G16="APPROVED",H16="APPROVED"),AND(G16="APPROVED",H16="")),F16,0)) -> 0
A17: 12 | I17: =IF(OR(G17="REJECTED",G17=""),0,IF(OR(AND(G17="APPROVED",H17="APPROVED"),AND(G17="APPROVED",H17="")),F17,0)) -> 0
A18: 13 | I18: =IF(OR(G18="REJECTED",G18=""),0,IF(OR(AND(G18="APPROVED",H18="APPROVED"),AND(G18="APPROVED",H18="")),F18,0)) -> 0
A19: 14 | I19: =IF(OR(G19="REJECTED",G19=""),0,IF(OR(AND(G19="APPROVED",H19="APPROVED"),AND(G19="APPROVED",H19="")),F19,0)) -> 0
A20: 15 | I20: =IF(OR(G20="REJECTED",G20=""),0,IF(OR(AND(G20="APPROVED",H20="APPROVED"),AND(G20="APPROVED",H20="")),F20,0)) -> 0
A21: 16 | I21: =IF(OR(G21="REJECTED",G21=""),0,IF(OR(AND(G21="APPROVED",H21="APPROVED"),AND(G21="APPROVED",H21="")),F21,0)) -> 0
A22: 17 | I22: =IF(OR(G22="REJECTED",G22=""),0,IF(OR(AND(G22="APPROVED",H22="APPROVED"),AND(G22="APPROVED",H22="")),F22,0)) -> 0
A23: 18 | I23: =IF(OR(G23="REJECTED",G23=""),0,IF(OR(AND(G23="APPROVED",H23="APPROVED"),AND(G23="APPROVED",H23="")),F23,0)) -> 0
A24: 19 | I24: =IF(OR(G24="REJECTED",G24=""),0,IF(OR(AND(G24="APPROVED",H24="APPROVED"),AND(G24="APPROVED",H24="")),F24,0)) -> 0
A25: 20 | I25: =IF(OR(G25="REJECTED",G25=""),0,IF(OR(AND(G25="APPROVED",H25="APPROVED"),AND(G25="APPROVED",H25="")),F25,0)) -> 0
A26: TOTALS | F26: =SUM(F8:F25) -> 590700 | I26: =IF(OR(G26="REJECTED",G26=""),0,IF(OR(AND(G26="APPROVED",H26="APPROVED"),AND(G26="APPROVED",H26="")),F26,0)) -> 0
A28: DAILY WALLET SUMMARY
A29: Opening Balance: | D29: =B5 -> 1795811
A30: Total Amount Requested: | D30: =F26 -> 590700
A31: Total Amount Released: | D31: =I26 -> 0
A32: Pending Approval: | D32: =SUMIFS(F8:F25,G8:G25,"PENDING")+SUMIFS(F8:F25,G8:G25,"APPROVED",H8:H25,"PENDING") -> 0
A33: Rejected Amount: | D33: =SUMIF(G8:G25,"REJECTED",F8:F25)+SUMIFS(F8:F25,G8:G25,"APPROVED",H8:H25,"REJECTED") -> 45000
A34: Closing Balance: | D34: =D29-D31 -> 1795811
A37: AUTHORIZATION SIGNATURES
A39: Prepared By: Tina-Randa | D39: Reviewed By (Finance): | G39: CFO APPROVAL: | H39: ENOW | J39: CEO APPROVAL: | K39: DERICK FONDERSON
A40: Name/Date: 11/06/2026 | D40: Name/Date: | G40: Name/Date: | H40: 46184 | J40: Name/Date: | K40: 46184
A41: NOTE: CFO can approve expenses up to a defined threshold without CEO approval. Expenses above threshold require both CFO and CEO approval.
E50: 226370 | F50: MAVIANCE DEDUCTED US WITHOUT MAKING PAYMENTS
E51: 102409 | F51: NOT ACCOUNTED FOR

Sheet 12-06-2026
A1: INTEL HRC - ELECTRONIC CASH WALLET EXPENSE TRACKER
A2: DAILY CASH EXPENSE APPROVAL & TRACKING SHEET
A4: WALLET INFORMATION
A5: Opening Balance: | B5: ='11-06-2026'!D34 -> 1795811 | D5: Date:12/06/2026 | H5: Wallet ID: | I5: MAVIANCE
A6: Maviance Balance:
A7: S/N | B7: DATE | C7: DESCRIPTION/PURPOSE | D7: BENEFICIARY | E7: CATEGORY | F7: AMOUNT REQUESTED (XAF) | G7: CFO APPROVAL | H7: CEO APPROVAL | I7: AMOUNT RELEASED (XAF) | J7: PAYMENT METHOD | K7: RECEIPT/REF NO. | L7: REMARKS
A8: 1 | B8: 46185 | C8: SALARY - CYNTHIA STEWART | D8: GAMING IQ | E8: Client Expense | F8: 34626 | G8: APPROVED | H8: APPROVED | I8: =IF(OR(G8="REJECTED",G8=""),0,IF(OR(AND(G8="APPROVED",H8="APPROVED"),AND(G8="APPROVED",H8="")),F8,0)) -> 34626
A9: 2 | B9: 46185 | C9: SALARY - AURELIE SANDRA | D9: GAMING IQ | E9: Client Expense | F9: 90656 | G9: APPROVED | H9: APPROVED | I9: =IF(OR(G9="REJECTED",G9=""),0,IF(OR(AND(G9="APPROVED",H9="APPROVED"),AND(G9="APPROVED",H9="")),F9,0)) -> 90656
A10: 3 | B10: 46185 | C10: INTERNET - STARLINK - HOME | D10: DNF | E10: Communication | F10: 56000 | G10: APPROVED | H10: APPROVED | I10: =IF(OR(G10="REJECTED",G10=""),0,IF(OR(AND(G10="APPROVED",H10="APPROVED"),AND(G10="APPROVED",H10="")),F10,0)) -> 56000
A11: 4 | B11: 46185 | C11: SALARY - RODRIGUE | D11: GAMING IQ | E11: Client Expense | F11: 70360 | G11: APPROVED | H11: APPROVED | I11: =IF(OR(G11="REJECTED",G11=""),0,IF(OR(AND(G11="APPROVED",H11="APPROVED"),AND(G11="APPROVED",H11="")),F11,0)) -> 70360
A12: 5 | I12: =IF(OR(G12="REJECTED",G12=""),0,IF(OR(AND(G12="APPROVED",H12="APPROVED"),AND(G12="APPROVED",H12="")),F12,0)) -> 0
A13: 6 | I13: =IF(OR(G13="REJECTED",G13=""),0,IF(OR(AND(G13="APPROVED",H13="APPROVED"),AND(G13="APPROVED",H13="")),F13,0)) -> 0
A14: 7 | I14: =IF(OR(G14="REJECTED",G14=""),0,IF(OR(AND(G14="APPROVED",H14="APPROVED"),AND(G14="APPROVED",H14="")),F14,0)) -> 0
A15: 8 | I15: =IF(OR(G15="REJECTED",G15=""),0,IF(OR(AND(G15="APPROVED",H15="APPROVED"),AND(G15="APPROVED",H15="")),F15,0)) -> 0
A16: 9 | I16: =IF(OR(G16="REJECTED",G16=""),0,IF(OR(AND(G16="APPROVED",H16="APPROVED"),AND(G16="APPROVED",H16="")),F16,0)) -> 0
A17: 10 | I17: =IF(OR(G17="REJECTED",G17=""),0,IF(OR(AND(G17="APPROVED",H17="APPROVED"),AND(G17="APPROVED",H17="")),F17,0)) -> 0
A18: 11 | I18: =IF(OR(G18="REJECTED",G18=""),0,IF(OR(AND(G18="APPROVED",H18="APPROVED"),AND(G18="APPROVED",H18="")),F18,0)) -> 0
A19: 12 | I19: =IF(OR(G19="REJECTED",G19=""),0,IF(OR(AND(G19="APPROVED",H19="APPROVED"),AND(G19="APPROVED",H19="")),F19,0)) -> 0
A20: 13 | I20: =IF(OR(G20="REJECTED",G20=""),0,IF(OR(AND(G20="APPROVED",H20="APPROVED"),AND(G20="APPROVED",H20="")),F20,0)) -> 0
A21: 14 | I21: =IF(OR(G21="REJECTED",G21=""),0,IF(OR(AND(G21="APPROVED",H21="APPROVED"),AND(G21="APPROVED",H21="")),F21,0)) -> 0
A22: 15 | I22: =IF(OR(G22="REJECTED",G22=""),0,IF(OR(AND(G22="APPROVED",H22="APPROVED"),AND(G22="APPROVED",H22="")),F22,0)) -> 0
A23: 16 | I23: =IF(OR(G23="REJECTED",G23=""),0,IF(OR(AND(G23="APPROVED",H23="APPROVED"),AND(G23="APPROVED",H23="")),F23,0)) -> 0
... A27: 20 | I27: =IF(OR(G27="REJECTED",G27=""),0,IF(OR(AND(G27="APPROVED",H27="APPROVED"),AND(G27="APPROVED",H27="")),F27,0)) -> 0
A28: TOTALS | F28: =SUM(F8:F27) -> 251642 | I28: =SUMIF(G8:G27,"APPROVED",I8:I27) -> 251642
A30: DAILY WALLET SUMMARY
A31: Opening Balance: | D31: =B5 -> 1795811
A32: Total Amount Requested: | D32: =F28 -> 251642
A33: Total Amount Released: | D33: =I28 -> 251642
A34: Pending Approval: | D34: =SUMIFS(F8:F27,G8:G27,"PENDING")+SUMIFS(F8:F27,G8:G27,"APPROVED",H8:H27,"PENDING") -> 0
A35: Rejected Amount: | D35: =SUMIF(G8:G27,"REJECTED",F8:F27)+SUMIFS(F8:F27,G8:G27,"APPROVED",H8:H27,"REJECTED") -> 0
A36: Closing Balance: | D36: =D31-D33 -> 1544169
A39: AUTHORIZATION SIGNATURES
A41: Prepared By: Tina-Randa | D41: Reviewed By (Finance): | G41: CFO APPROVAL: | H41: ENOW | J41: CEO APPROVAL: | K41: DERICK FONDERSON
A42: Name/Date: 11/06/2026 | D42: Name/Date: | G42: Name/Date: | H42: 46184 | J42: Name/Date: | K42: 46184
A43: NOTE: CFO can approve expenses up to a defined threshold without CEO approval. Expenses above threshold require both CFO and CEO approval.

Sheet 13-06-2026
A1: INTEL HRC - ELECTRONIC CASH WALLET EXPENSE TRACKER
A2: DAILY CASH EXPENSE APPROVAL & TRACKING SHEET
A4: WALLET INFORMATION
A5: Opening Balance: | B5: ='12-06-2026'!D36 -> 1544169 | D5: Date:13/06/2026 | H5: Wallet ID: | I5: MAVIANCE
A7: S/N | B7: DATE | C7: DESCRIPTION/PURPOSE | D7: BENEFICIARY | E7: CATEGORY | F7: AMOUNT REQUESTED (XAF) | G7: CFO APPROVAL | H7: CEO APPROVAL | I7: AMOUNT RELEASED (XAF) | J7: PAYMENT METHOD | K7: RECEIPT/REF NO. | L7: REMARKS
A8: 1 | I8: =IF(OR(G8="REJECTED",G8=""),0,IF(OR(AND(G8="APPROVED",H8="APPROVED"),AND(G8="APPROVED",H8="")),F8,0)) -> 0
A9: 2 | I9: =IF(OR(G9="REJECTED",G9=""),0,IF(OR(AND(G9="APPROVED",H9="APPROVED"),AND(G9="APPROVED",H9="")),F9,0)) -> 0
A10: 3 | I10: =IF(OR(G10="REJECTED",G10=""),0,IF(OR(AND(G10="APPROVED",H10="APPROVED"),AND(G10="APPROVED",H10="")),F10,0)) -> 0
A11: 4 | I11: =IF(OR(G11="REJECTED",G11=""),0,IF(OR(AND(G11="APPROVED",H11="APPROVED"),AND(G11="APPROVED",H11="")),F11,0)) -> 0
A12: 5 | I12: =IF(OR(G12="REJECTED",G12=""),0,IF(OR(AND(G12="APPROVED",H12="APPROVED"),AND(G12="APPROVED",H12="")),F12,0)) -> 0
A13: 6 | I13: =IF(OR(G13="REJECTED",G13=""),0,IF(OR(AND(G13="APPROVED",H13="APPROVED"),AND(G13="APPROVED",H13="")),F13,0)) -> 0
A14: 7 | I14: =IF(OR(G14="REJECTED",G14=""),0,IF(OR(AND(G14="APPROVED",H14="APPROVED"),AND(G14="APPROVED",H14="")),F14,0)) -> 0
A15: 8 | I15: =IF(OR(G15="REJECTED",G15=""),0,IF(OR(AND(G15="APPROVED",H15="APPROVED"),AND(G15="APPROVED",H15="")),F15,0)) -> 0
A16: 9 | I16: =IF(OR(G16="REJECTED",G16=""),0,IF(OR(AND(G16="APPROVED",H16="APPROVED"),AND(G16="APPROVED",H16="")),F16,0)) -> 0
A17: 10 | I17: =IF(OR(G17="REJECTED",G17=""),0,IF(OR(AND(G17="APPROVED",H17="APPROVED"),AND(G17="APPROVED",H17="")),F17,0)) -> 0
A18: 11 | I18: =IF(OR(G18="REJECTED",G18=""),0,IF(OR(AND(G18="APPROVED",H18="APPROVED"),AND(G18="APPROVED",H18="")),F18,0)) -> 0
A19: 12 | I19: =IF(OR(G19="REJECTED",G19=""),0,IF(OR(AND(G19="APPROVED",H19="APPROVED"),AND(G19="APPROVED",H19="")),F19,0)) -> 0
... A27: 20 | I27: =IF(OR(G27="REJECTED",G27=""),0,IF(OR(AND(G27="APPROVED",H27="APPROVED"),AND(G27="APPROVED",H27="")),F27,0)) -> 0
A28: TOTALS | F28: =SUM(F8:F27) -> 0 | I28: =SUMIF(G8:G27,"APPROVED",I8:I27) -> 0
A30: DAILY WALLET SUMMARY
A31: Opening Balance: | D31: =B5 -> 1544169
A32: Total Amount Requested: | D32: =F28 -> 0
A33: Total Amount Released: | D33: =I28 -> 0
A34: Pending Approval: | D34: =SUMIFS(F8:F27,G8:G27,"PENDING")+SUMIFS(F8:F27,G8:G27,"APPROVED",H8:H27,"PENDING") -> 0
A35: Rejected Amount: | D35: =SUMIF(G8:G27,"REJECTED",F8:F27)+SUMIFS(F8:F27,G8:G27,"APPROVED",H8:H27,"REJECTED") -> 0
A36: Closing Balance: | D36: =D31-D33 -> 1544169
A39: AUTHORIZATION SIGNATURES
A41: Prepared By: Tina-Randa | D41: Reviewed By (Finance): | G41: CFO APPROVAL: | H41: ENOW | J41: CEO APPROVAL: | K41: DERICK FONDERSON
A42: Name/Date: 11/06/2026 | D42: Name/Date: | G42: Name/Date: | H42: 46184 | J42: Name/Date: | K42: 46184
A43: NOTE: CFO can approve expenses up to a defined threshold without CEO approval. Expenses above threshold require both CFO and CEO approval.

Sheet 14-06-2026
A1: INTEL HRC - ELECTRONIC CASH WALLET EXPENSE TRACKER
A2: DAILY CASH EXPENSE APPROVAL & TRACKING SHEET
A4: WALLET INFORMATION
A5: Opening Balance: | B5: ='13-06-2026'!D36 -> 1544169 | D5: Date:14/06/2026 | H5: Wallet ID: | I5: MAVIANCE
A7: S/N | B7: DATE | C7: DESCRIPTION/PURPOSE | D7: BENEFICIARY | E7: CATEGORY | F7: AMOUNT REQUESTED (XAF) | G7: CFO APPROVAL | H7: CEO APPROVAL | I7: AMOUNT RELEASED (XAF) | J7: PAYMENT METHOD | K7: RECEIPT/REF NO. | L7: REMARKS
A8: 1 | I8: =IF(OR(G8="REJECTED",G8=""),0,IF(OR(AND(G8="APPROVED",H8="APPROVED"),AND(G8="APPROVED",H8="")),F8,0)) -> 0
A9: 2 | I9: =IF(OR(G9="REJECTED",G9=""),0,IF(OR(AND(G9="APPROVED",H9="APPROVED"),AND(G9="APPROVED",H9="")),F9,0)) -> 0
A10: 3 | I10: =IF(OR(G10="REJECTED",G10=""),0,IF(OR(AND(G10="APPROVED",H10="APPROVED"),AND(G10="APPROVED",H10="")),F10,0)) -> 0
A11: 4 | I11: =IF(OR(G11="REJECTED",G11=""),0,IF(OR(AND(G11="APPROVED",H11="APPROVED"),AND(G11="APPROVED",H11="")),F11,0)) -> 0
A12: 5 | I12: =IF(OR(G12="REJECTED",G12=""),0,IF(OR(AND(G12="APPROVED",H12="APPROVED"),AND(G12="APPROVED",H12="")),F12,0)) -> 0
A13: 6 | I13: =IF(OR(G13="REJECTED",G13=""),0,IF(OR(AND(G13="APPROVED",H13="APPROVED"),AND(G13="APPROVED",H13="")),F13,0)) -> 0
A14: 7 | I14: =IF(OR(G14="REJECTED",G14=""),0,IF(OR(AND(G14="APPROVED",H14="APPROVED"),AND(G14="APPROVED",H14="")),F14,0)) -> 0
A15: 8 | I15: =IF(OR(G15="REJECTED",G15=""),0,IF(OR(AND(G15="APPROVED",H15="APPROVED"),AND(G15="APPROVED",H15="")),F15,0)) -> 0
A16: 9 | I16: =IF(OR(G16="REJECTED",G16=""),0,IF(OR(AND(G16="APPROVED",H16="APPROVED"),AND(G16="APPROVED",H16="")),F16,0)) -> 0
A17: 10 | I17: =IF(OR(G17="REJECTED",G17=""),0,IF(OR(AND(G17="APPROVED",H17="APPROVED"),AND(G17="APPROVED",H17="")),F17,0)) -> 0
A18: 11 | I18: =IF(OR(G18="REJECTED",G18=""),0,IF(OR(AND(G18="APPROVED",H18="APPROVED"),AND(G18="APPROVED",H18="")),F18,0)) -> 0
A19: 12 | I19: =IF(OR(G19="REJECTED",G19=""),0,IF(OR(AND(G19="APPROVED",H19="APPROVED"),AND(G19="APPROVED",H19="")),F19,0)) -> 0
... A27: 20 | I27: =IF(OR(G27="REJECTED",G27=""),0,IF(OR(AND(G27="APPROVED",H27="APPROVED"),AND(G27="APPROVED",H27="")),F27,0)) -> 0
A28: TOTALS | F28: =SUM(F8:F27) -> 0 | I28: =SUMIF(G8:G27,"APPROVED",I8:I27) -> 0
A30: DAILY WALLET SUMMARY
A31: Opening Balance: | D31: =B5 -> 1544169
A32: Total Amount Requested: | D32: =F28 -> 0
A33: Total Amount Released: | D33: =I28 -> 0
A34: Pending Approval: | D34: =SUMIFS(F8:F27,G8:G27,"PENDING")+SUMIFS(F8:F27,G8:G27,"APPROVED",H8:H27,"PENDING") -> 0
A35: Rejected Amount: | D35: =SUMIF(G8:G27,"REJECTED",F8:F27)+SUMIFS(F8:F27,G8:G27,"APPROVED",H8:H27,"REJECTED") -> 0
A36: Closing Balance: | D36: =D31-D33 -> 1544169
A39: AUTHORIZATION SIGNATURES
A41: Prepared By: Tina-Randa | D41: Reviewed By (Finance): | G41: CFO APPROVAL: | H41: ENOW | J41: CEO APPROVAL: | K41: DERICK FONDERSON
A42: Name/Date: 11/06/2026 | D42: Name/Date: | G42: Name/Date: | H42: 46184 | J42: Name/Date: | K42: 46184
A43: NOTE: CFO can approve expenses up to a defined threshold without CEO approval. Expenses above threshold require both CFO and CEO approval.

Sheet 15-06-2026
A1: INTEL HRC - ELECTRONIC CASH WALLET EXPENSE TRACKER
A2: DAILY CASH EXPENSE APPROVAL & TRACKING SHEET
A4: WALLET INFORMATION
A5: Opening Balance: | B5: ='14-06-2026'!D36 -> 1544169 | D5: Date:15/06/2026 | H5: Wallet ID: | I5: MAVIANCE
A7: S/N | B7: DATE | C7: DESCRIPTION/PURPOSE | D7: BENEFICIARY | E7: CATEGORY | F7: AMOUNT REQUESTED (XAF) | G7: CFO APPROVAL | H7: CEO APPROVAL | I7: AMOUNT RELEASED (XAF) | J7: PAYMENT METHOD | K7: RECEIPT/REF NO. | L7: REMARKS
I8: =IF(OR(G8="REJECTED",G8=""),0,IF(OR(AND(G8="APPROVED",H8="APPROVED"),AND(G8="APPROVED",H8="")),F8,0)) -> 0
I9: =IF(OR(G9="REJECTED",G9=""),0,IF(OR(AND(G9="APPROVED",H9="APPROVED"),AND(G9="APPROVED",H9="")),F9,0)) -> 0
I10: =IF(OR(G10="REJECTED",G10=""),0,IF(OR(AND(G10="APPROVED",H10="APPROVED"),AND(G10="APPROVED",H10="")),F10,0)) -> 0
I11: =IF(OR(G11="REJECTED",G11=""),0,IF(OR(AND(G11="APPROVED",H11="APPROVED"),AND(G11="APPROVED",H11="")),F11,0)) -> 0
I12: =IF(OR(G12="REJECTED",G12=""),0,IF(OR(AND(G12="APPROVED",H12="APPROVED"),AND(G12="APPROVED",H12="")),F12,0)) -> 0
I13: =IF(OR(G13="REJECTED",G13=""),0,IF(OR(AND(G13="APPROVED",H13="APPROVED"),AND(G13="APPROVED",H13="")),F13,0)) -> 0
I14: =IF(OR(G14="REJECTED",G14=""),0,IF(OR(AND(G14="APPROVED",H14="APPROVED"),AND(G14="APPROVED",H14="")),F14,0)) -> 0
I15: =IF(OR(G15="REJECTED",G15=""),0,IF(OR(AND(G15="APPROVED",H15="APPROVED"),AND(G15="APPROVED",H15="")),F15,0)) -> 0
I16: =IF(OR(G16="REJECTED",G16=""),0,IF(OR(AND(G16="APPROVED",H16="APPROVED"),AND(G16="APPROVED",H16="")),F16,0)) -> 0
I17: =IF(OR(G17="REJECTED",G17=""),0,IF(OR(AND(G17="APPROVED",H17="APPROVED"),AND(G17="APPROVED",H17="")),F17,0)) -> 0
I18: =IF(OR(G18="REJECTED",G18=""),0,IF(OR(AND(G18="APPROVED",H18="APPROVED"),AND(G18="APPROVED",H18="")),F18,0)) -> 0
I19: =IF(OR(G19="REJECTED",G19=""),0,IF(OR(AND(G19="APPROVED",H19="APPROVED"),AND(G19="APPROVED",H19="")),F19,0)) -> 0
... I22: =IF(OR(G22="REJECTED",G22=""),0,IF(OR(AND(G22="APPROVED",H22="APPROVED"),AND(G22="APPROVED",H22="")),F22,0)) -> 0
A23: TOTALS | F23: =SUM(F8:F22) -> 0 | I23: =SUMIF(G8:G22,"APPROVED",I8:I22) -> 0
A25: DAILY WALLET SUMMARY
A26: Opening Balance: | D26: =B5 -> 1544169
A27: Total Amount Requested: | D27: =F23 -> 0
A28: Total Amount Released: | D28: =I23 -> 0
A29: Pending Approval: | D29: =SUMIFS(F8:F22,G8:G22,"PENDING")+SUMIFS(F8:F22,G8:G22,"APPROVED",H8:H22,"PENDING") -> 0
A30: Rejected Amount: | D30: =SUMIF(G8:G22,"REJECTED",F8:F22)+SUMIFS(F8:F22,G8:G22,"APPROVED",H8:H22,"REJECTED") -> 0
A31: Closing Balance: | D31: =D26-D28 -> 1544169
A34: AUTHORIZATION SIGNATURES
A36: Prepared By: Tina-Randa | D36: Reviewed By (Finance): | G36: CFO APPROVAL: | H36: ENOW | J36: CEO APPROVAL: | K36: DERICK FONDERSON
A37: Name/Date: 11/06/2026 | D37: Name/Date: | G37: Name/Date: | H37: 46184 | J37: Name/Date: | K37: 46184
A38: NOTE: CFO can approve expenses up to a defined threshold without CEO approval. Expenses above threshold require both CFO and CEO approval.

Sheet 16-06-2026
A1: INTEL HRC - ELECTRONIC CASH WALLET EXPENSE TRACKER
A2: DAILY CASH EXPENSE APPROVAL & TRACKING SHEET
A4: WALLET INFORMATION
A5: Opening Balance: | B5: ='15-06-2026'!D31 -> 1544169 | D5: Date:16/06/2026 | H5: Wallet ID: | I5: MAVIANCE
A7: S/N | B7: DATE | C7: DESCRIPTION/PURPOSE | D7: BENEFICIARY | E7: CATEGORY | F7: AMOUNT REQUESTED (XAF) | G7: CFO APPROVAL | H7: CEO APPROVAL | I7: AMOUNT RELEASED (XAF) | J7: PAYMENT METHOD | K7: RECEIPT/REF NO. | L7: REMARKS
A8: 1 | B8: 46189 | C8: SALARY | D8: 3C CAMEROUN | E8: Client Expense | F8: 64370 | G8: APPROVED | H8: APPROVED | I8: =IF(OR(G8="REJECTED",G8=""),0,IF(OR(AND(G8="APPROVED",H8="APPROVED"),AND(G8="APPROVED",H8="")),F8,0)) -> 64370 | J8: Mobile Money
A9: 2 | B9: 46189 | C9: EXTRA COST STARLINK - DNF | D9: FRANCIS | E9: Communication | F9: 5500 | G9: APPROVED | H9: APPROVED | I9: =IF(OR(G9="REJECTED",G9=""),0,IF(OR(AND(G9="APPROVED",H9="APPROVED"),AND(G9="APPROVED",H9="")),F9,0)) -> 5500 | J9: Mobile Money
A10: 3 | B10: 46189 | C10: FRAIS DE TAXI | D10: ERNEST | E10: Transport | F10: 3100 | G10: APPROVED | H10: APPROVED | I10: =IF(OR(G10="REJECTED",G10=""),0,IF(OR(AND(G10="APPROVED",H10="APPROVED"),AND(G10="APPROVED",H10="")),F10,0)) -> 3100 | J10: Mobile Money
A11: 4 | B11: 46189 | C11: DESIRE | D11: DESIRE | E11: Transport | F11: 10200 | G11: APPROVED | H11: APPROVED | I11: =IF(OR(G11="REJECTED",G11=""),0,IF(OR(AND(G11="APPROVED",H11="APPROVED"),AND(G11="APPROVED",H11="")),F11,0)) -> 10200 | J11: Mobile Money
A12: 5 | I12: =IF(OR(G12="REJECTED",G12=""),0,IF(OR(AND(G12="APPROVED",H12="APPROVED"),AND(G12="APPROVED",H12="")),F12,0)) -> 0
A13: 6 | I13: =IF(OR(G13="REJECTED",G13=""),0,IF(OR(AND(G13="APPROVED",H13="APPROVED"),AND(G13="APPROVED",H13="")),F13,0)) -> 0
A14: 7 | I14: =IF(OR(G14="REJECTED",G14=""),0,IF(OR(AND(G14="APPROVED",H14="APPROVED"),AND(G14="APPROVED",H14="")),F14,0)) -> 0
A15: 8 | I15: =IF(OR(G15="REJECTED",G15=""),0,IF(OR(AND(G15="APPROVED",H15="APPROVED"),AND(G15="APPROVED",H15="")),F15,0)) -> 0
A16: 9 | I16: =IF(OR(G16="REJECTED",G16=""),0,IF(OR(AND(G16="APPROVED",H16="APPROVED"),AND(G16="APPROVED",H16="")),F16,0)) -> 0
A17: 10 | I17: =IF(OR(G17="REJECTED",G17=""),0,IF(OR(AND(G17="APPROVED",H17="APPROVED"),AND(G17="APPROVED",H17="")),F17,0)) -> 0
A18: 11 | I18: =IF(OR(G18="REJECTED",G18=""),0,IF(OR(AND(G18="APPROVED",H18="APPROVED"),AND(G18="APPROVED",H18="")),F18,0)) -> 0
A19: 12 | I19: =IF(OR(G19="REJECTED",G19=""),0,IF(OR(AND(G19="APPROVED",H19="APPROVED"),AND(G19="APPROVED",H19="")),F19,0)) -> 0
A20: 13 | I20: =IF(OR(G20="REJECTED",G20=""),0,IF(OR(AND(G20="APPROVED",H20="APPROVED"),AND(G20="APPROVED",H20="")),F20,0)) -> 0
A21: 14 | I21: =IF(OR(G21="REJECTED",G21=""),0,IF(OR(AND(G21="APPROVED",H21="APPROVED"),AND(G21="APPROVED",H21="")),F21,0)) -> 0
A22: 15 | I22: =IF(OR(G22="REJECTED",G22=""),0,IF(OR(AND(G22="APPROVED",H22="APPROVED"),AND(G22="APPROVED",H22="")),F22,0)) -> 0
A23: 16 | I23: =IF(OR(G23="REJECTED",G23=""),0,IF(OR(AND(G23="APPROVED",H23="APPROVED"),AND(G23="APPROVED",H23="")),F23,0)) -> 0
... A27: 20 | I27: =IF(OR(G27="REJECTED",G27=""),0,IF(OR(AND(G27="APPROVED",H27="APPROVED"),AND(G27="APPROVED",H27="")),F27,0)) -> 0
A28: TOTALS | F28: =SUM(F8:F27) -> 83170 | I28: =SUMIF(G8:G27,"APPROVED",I8:I27) -> 83170
A30: DAILY WALLET SUMMARY
A31: Opening Balance: | D31: =B5 -> 1544169
A32: Total Amount Requested: | D32: =F28 -> 83170
A33: Total Amount Released: | D33: =I28 -> 83170
A34: Pending Approval: | D34: =SUMIFS(F8:F27,G8:G27,"PENDING")+SUMIFS(F8:F27,G8:G27,"APPROVED",H8:H27,"PENDING") -> 0
A35: Rejected Amount: | D35: =SUMIF(G8:G27,"REJECTED",F8:F27)+SUMIFS(F8:F27,G8:G27,"APPROVED",H8:H27,"REJECTED") -> 0
A36: Closing Balance: | D36: =D31-D33 -> 1460999
A39: AUTHORIZATION SIGNATURES
A41: Prepared By: Tina-Randa | D41: Reviewed By (Finance): | G41: CFO APPROVAL: | H41: ENOW | J41: CEO APPROVAL: | K41: DERICK FONDERSON
A42: Name/Date: 11/06/2026 | D42: Name/Date: | G42: Name/Date: | H42: 46184 | J42: Name/Date: | K42: 46184
A43: NOTE: CFO can approve expenses up to a defined threshold without CEO approval. Expenses above threshold require both CFO and CEO approval.

Sheet 17-06-2026
A1: INTEL HRC - ELECTRONIC CASH WALLET EXPENSE TRACKER
A2: DAILY CASH EXPENSE APPROVAL & TRACKING SHEET
A4: WALLET INFORMATION
A5: Opening Balance: | B5: ='16-06-2026'!D36 -> 1460999 | D5: Date:11/06/2026 | H5: Wallet ID: | I5: MAVIANCE
A7: S/N | B7: DATE | C7: DESCRIPTION/PURPOSE | D7: BENEFICIARY | E7: CATEGORY | F7: AMOUNT REQUESTED (XAF) | G7: CFO APPROVAL | H7: CEO APPROVAL | I7: AMOUNT RELEASED (XAF) | J7: PAYMENT METHOD | K7: RECEIPT/REF NO. | L7: REMARKS
A8: 1 | I8: =IF(OR(G8="REJECTED",G8=""),0,IF(OR(AND(G8="APPROVED",H8="APPROVED"),AND(G8="APPROVED",H8="")),F8,0)) -> 0
A9: 2 | I9: =IF(OR(G9="REJECTED",G9=""),0,IF(OR(AND(G9="APPROVED",H9="APPROVED"),AND(G9="APPROVED",H9="")),F9,0)) -> 0
A10: 3 | I10: =IF(OR(G10="REJECTED",G10=""),0,IF(OR(AND(G10="APPROVED",H10="APPROVED"),AND(G10="APPROVED",H10="")),F10,0)) -> 0
A11: 4 | I11: =IF(OR(G11="REJECTED",G11=""),0,IF(OR(AND(G11="APPROVED",H11="APPROVED"),AND(G11="APPROVED",H11="")),F11,0)) -> 0
A12: 5 | I12: =IF(OR(G12="REJECTED",G12=""),0,IF(OR(AND(G12="APPROVED",H12="APPROVED"),AND(G12="APPROVED",H12="")),F12,0)) -> 0
A13: 6 | I13: =IF(OR(G13="REJECTED",G13=""),0,IF(OR(AND(G13="APPROVED",H13="APPROVED"),AND(G13="APPROVED",H13="")),F13,0)) -> 0
A14: 7 | I14: =IF(OR(G14="REJECTED",G14=""),0,IF(OR(AND(G14="APPROVED",H14="APPROVED"),AND(G14="APPROVED",H14="")),F14,0)) -> 0
A15: 8 | I15: =IF(OR(G15="REJECTED",G15=""),0,IF(OR(AND(G15="APPROVED",H15="APPROVED"),AND(G15="APPROVED",H15="")),F15,0)) -> 0
A16: 9 | I16: =IF(OR(G16="REJECTED",G16=""),0,IF(OR(AND(G16="APPROVED",H16="APPROVED"),AND(G16="APPROVED",H16="")),F16,0)) -> 0
A17: 10 | I17: =IF(OR(G17="REJECTED",G17=""),0,IF(OR(AND(G17="APPROVED",H17="APPROVED"),AND(G17="APPROVED",H17="")),F17,0)) -> 0
A18: 11 | I18: =IF(OR(G18="REJECTED",G18=""),0,IF(OR(AND(G18="APPROVED",H18="APPROVED"),AND(G18="APPROVED",H18="")),F18,0)) -> 0
A19: 12 | I19: =IF(OR(G19="REJECTED",G19=""),0,IF(OR(AND(G19="APPROVED",H19="APPROVED"),AND(G19="APPROVED",H19="")),F19,0)) -> 0
... A27: 20 | I27: =IF(OR(G27="REJECTED",G27=""),0,IF(OR(AND(G27="APPROVED",H27="APPROVED"),AND(G27="APPROVED",H27="")),F27,0)) -> 0
A28: TOTALS | F28: =SUM(F8:F27) -> 0 | I28: =SUMIF(G8:G27,"APPROVED",I8:I27) -> 0
A30: DAILY WALLET SUMMARY
A31: Opening Balance: | D31: =B5 -> 1460999
A32: Total Amount Requested: | D32: =F28 -> 0
A33: Total Amount Released: | D33: =I28 -> 0
A34: Pending Approval: | D34: =SUMIFS(F8:F27,G8:G27,"PENDING")+SUMIFS(F8:F27,G8:G27,"APPROVED",H8:H27,"PENDING") -> 0
A35: Rejected Amount: | D35: =SUMIF(G8:G27,"REJECTED",F8:F27)+SUMIFS(F8:F27,G8:G27,"APPROVED",H8:H27,"REJECTED") -> 0
A36: Closing Balance: | D36: =D31-D33 -> 1460999
A39: AUTHORIZATION SIGNATURES
A41: Prepared By: Tina-Randa | D41: Reviewed By (Finance): | G41: CFO APPROVAL: | H41: ENOW | J41: CEO APPROVAL: | K41: DERICK FONDERSON
A42: Name/Date: 11/06/2026 | D42: Name/Date: | G42: Name/Date: | H42: 46184 | J42: Name/Date: | K42: 46184
A43: NOTE: CFO can approve expenses up to a defined threshold without CEO approval. Expenses above threshold require both CFO and CEO approval.
A49: maviance balance as at 18/06/2026 | B49: 905850

Sheet 19-06-2026 
A1: INTEL HRC - ELECTRONIC CASH WALLET EXPENSE TRACKER
A2: DAILY CASH EXPENSE APPROVAL & TRACKING SHEET
A4: WALLET INFORMATION
A5: Opening Balance: | B5: ='16-06-2026'!D36 -> 1460999 | D5: Date:11/06/2026 | H5: Wallet ID: | I5: MAVIANCE
A7: S/N | B7: DATE | C7: DESCRIPTION/PURPOSE | D7: BENEFICIARY | E7: CATEGORY | F7: AMOUNT REQUESTED (XAF) | G7: CFO APPROVAL | H7: CEO APPROVAL | I7: AMOUNT RELEASED (XAF) | J7: PAYMENT METHOD | K7: RECEIPT/REF NO. | L7: REMARKS
A8: 1 | B8: 46192 | C8: CAM WATER BUREAU - YDE | D8: TINA | E8: Utilities | F8: 2677 | I8: =IF(OR(G8="REJECTED",G8=""),0,IF(OR(AND(G8="APPROVED",H8="APPROVED"),AND(G8="APPROVED",H8="")),F8,0)) -> 0
A9: 2 | B9: 46192 | C9: CAM WATER BUREUA - DLA | D9: TINA | E9: Utilities | F9: 24342 | I9: =IF(OR(G9="REJECTED",G9=""),0,IF(OR(AND(G9="APPROVED",H9="APPROVED"),AND(G9="APPROVED",H9="")),F9,0)) -> 0
A10: 3 | B10: 46192 | C10: ENEO YDE | D10: TINA | E10: Utilities | F10: 26095 | I10: =IF(OR(G10="REJECTED",G10=""),0,IF(OR(AND(G10="APPROVED",H10="APPROVED"),AND(G10="APPROVED",H10="")),F10,0)) -> 0
A11: 4 | B11: 46192 | C11: IBSIRE CORP - STARLINK RENTALS | D11: IBSIRE CORP | E11: Communication | F11: 45000 | I11: =IF(OR(G11="REJECTED",G11=""),0,IF(OR(AND(G11="APPROVED",H11="APPROVED"),AND(G11="APPROVED",H11="")),F11,0)) -> 0
A12: 5 | B12: 46192 | C12: SENDING FEE WWF DOCUMENT | D12: DESIRE | E12: Transport | F12: 1000 | I12: =IF(OR(G12="REJECTED",G12=""),0,IF(OR(AND(G12="APPROVED",H12="APPROVED"),AND(G12="APPROVED",H12="")),F12,0)) -> 0
A13: 6 | B13: 46192 | C13: STARLINK NEW SUBSCRIPTION | D13: FRANCIS | E13: Communication | F13: 5500 | I13: =IF(OR(G13="REJECTED",G13=""),0,IF(OR(AND(G13="APPROVED",H13="APPROVED"),AND(G13="APPROVED",H13="")),F13,0)) -> 0
A14: 7 | B14: 46192 | C14: LAPTOP MOUSE | D14: ENOW | E14: Supplies | F14: 15000 | I14: =IF(OR(G14="REJECTED",G14=""),0,IF(OR(AND(G14="APPROVED",H14="APPROVED"),AND(G14="APPROVED",H14="")),F14,0)) -> 0
A15: 8 | B15: 46192 | C15: LAPTOP BAG | D15: CFO | E15: Supplies | F15: 15000 | I15: =IF(OR(G15="REJECTED",G15=""),0,IF(OR(AND(G15="APPROVED",H15="APPROVED"),AND(G15="APPROVED",H15="")),F15,0)) -> 0
A16: 9 | B16: 46192 | C16: LAPTOP BAG STICKER | D16: CFO | E16: Supplies | F16: 5000 | I16: =IF(OR(G16="REJECTED",G16=""),0,IF(OR(AND(G16="APPROVED",H16="APPROVED"),AND(G16="APPROVED",H16="")),F16,0)) -> 0
A17: 10 | B17: 46192 | C17: MISSION | D17: I ENG | E17: Client Expense | F17: 170000 | I17: =IF(OR(G17="REJECTED",G17=""),0,IF(OR(AND(G17="APPROVED",H17="APPROVED"),AND(G17="APPROVED",H17="")),F17,0)) -> 0
A18: 11 | B18: 46192 | C18: SENDING FEE DHL EMPLOYEE VISAS | D18: DESIRE | E18: Transport | F18: 1000 | I18: =IF(OR(G18="REJECTED",G18=""),0,IF(OR(AND(G18="APPROVED",H18="APPROVED"),AND(G18="APPROVED",H18="")),F18,0)) -> 0
I19: =IF(OR(G19="REJECTED",G19=""),0,IF(OR(AND(G19="APPROVED",H19="APPROVED"),AND(G19="APPROVED",H19="")),F19,0)) -> 0
I20: =IF(OR(G20="REJECTED",G20=""),0,IF(OR(AND(G20="APPROVED",H20="APPROVED"),AND(G20="APPROVED",H20="")),F20,0)) -> 0
I21: =IF(OR(G21="REJECTED",G21=""),0,IF(OR(AND(G21="APPROVED",H21="APPROVED"),AND(G21="APPROVED",H21="")),F21,0)) -> 0
I22: =IF(OR(G22="REJECTED",G22=""),0,IF(OR(AND(G22="APPROVED",H22="APPROVED"),AND(G22="APPROVED",H22="")),F22,0)) -> 0
I23: =IF(OR(G23="REJECTED",G23=""),0,IF(OR(AND(G23="APPROVED",H23="APPROVED"),AND(G23="APPROVED",H23="")),F23,0)) -> 0
I24: =IF(OR(G24="REJECTED",G24=""),0,IF(OR(AND(G24="APPROVED",H24="APPROVED"),AND(G24="APPROVED",H24="")),F24,0)) -> 0
I25: =IF(OR(G25="REJECTED",G25=""),0,IF(OR(AND(G25="APPROVED",H25="APPROVED"),AND(G25="APPROVED",H25="")),F25,0)) -> 0
I26: =IF(OR(G26="REJECTED",G26=""),0,IF(OR(AND(G26="APPROVED",H26="APPROVED"),AND(G26="APPROVED",H26="")),F26,0)) -> 0
I27: =IF(OR(G27="REJECTED",G27=""),0,IF(OR(AND(G27="APPROVED",H27="APPROVED"),AND(G27="APPROVED",H27="")),F27,0)) -> 0
A28: TOTALS | F28: =SUM(F8:F27) -> 310614 | I28: =SUMIF(G8:G27,"APPROVED",I8:I27) -> 0
A30: DAILY WALLET SUMMARY
A31: Opening Balance: | D31: =B5 -> 1460999
A32: Total Amount Requested: | D32: =F28 -> 310614
A33: Total Amount Released: | D33: =I28 -> 0
A34: Pending Approval: | D34: =SUMIFS(F8:F27,G8:G27,"PENDING")+SUMIFS(F8:F27,G8:G27,"APPROVED",H8:H27,"PENDING") -> 0
A35: Rejected Amount: | D35: =SUMIF(G8:G27,"REJECTED",F8:F27)+SUMIFS(F8:F27,G8:G27,"APPROVED",H8:H27,"REJECTED") -> 0
A36: Closing Balance: | D36: =D31-D33 -> 1460999
A39: AUTHORIZATION SIGNATURES
A41: Prepared By: Tina-Randa | D41: Reviewed By (Finance): | G41: CFO APPROVAL: | H41: ENOW | J41: CEO APPROVAL: | K41: DERICK FONDERSON
A42: Name/Date: 11/06/2026 | D42: Name/Date: | G42: Name/Date: | H42: 46184 | J42: Name/Date: | K42: 46184
A43: NOTE: CFO can approve expenses up to a defined threshold without CEO approval. Expenses above threshold require both CFO and CEO approval.
A49: maviance balance as at 18/06/2026 | B49: 905850
